queen/__init__.py
queen/client.py
queen/py.typed
queen/types.py
queen/admin/__init__.py
queen/admin/admin.py
queen/buffer/__init__.py
queen/buffer/buffer_manager.py
queen/buffer/message_buffer.py
queen/builders/__init__.py
queen/builders/consume_builder.py
queen/builders/dlq_builder.py
queen/builders/operation_builder.py
queen/builders/push_builder.py
queen/builders/queue_builder.py
queen/builders/transaction_builder.py
queen/consumer/__init__.py
queen/consumer/consumer_manager.py
queen/http/__init__.py
queen/http/http_client.py
queen/http/load_balancer.py
queen/stream/__init__.py
queen/stream/stream_builder.py
queen/stream/stream_consumer.py
queen/stream/window.py
queen/utils/__init__.py
queen/utils/defaults.py
queen/utils/logger.py
queen/utils/uuid_gen.py
queen/utils/validation.py
queen_mq-0.12.0.dist-info/licenses/LICENSE
queen_mq-0.12.0.dist-info/METADATA
queen_mq-0.12.0.dist-info/WHEEL
queen_mq-0.12.0.dist-info/top_level.txt
queen_mq-0.12.0.dist-info/RECORD
