Metadata-Version: 2.4
Name: queen-mq
Version: 0.12.0
Summary: High-performance message queue client for Python backed by PostgreSQL
Author-email: Smartness <info@smartness.com>
License: Apache-2.0
Project-URL: Homepage, https://github.com/smartpricing/queen
Project-URL: Documentation, https://github.com/smartpricing/queen
Project-URL: Repository, https://github.com/smartpricing/queen
Project-URL: Issues, https://github.com/smartpricing/queen/issues
Keywords: message-queue,queue,broker,message-queue-system,fifo
Classifier: Development Status :: 4 - Beta
Classifier: Intended Audience :: Developers
Classifier: License :: OSI Approved :: Apache Software License
Classifier: Programming Language :: Python :: 3
Classifier: Programming Language :: Python :: 3.8
Classifier: Programming Language :: Python :: 3.9
Classifier: Programming Language :: Python :: 3.10
Classifier: Programming Language :: Python :: 3.11
Classifier: Programming Language :: Python :: 3.12
Classifier: Topic :: Software Development :: Libraries :: Python Modules
Classifier: Topic :: System :: Distributed Computing
Requires-Python: >=3.8
License-File: LICENSE
Requires-Dist: httpx>=0.27.0
Requires-Dist: typing-extensions>=4.0.0; python_version < "3.10"
Provides-Extra: dev
Requires-Dist: pytest>=7.0.0; extra == "dev"
Requires-Dist: pytest-asyncio>=0.21.0; extra == "dev"
Requires-Dist: asyncpg>=0.29.0; extra == "dev"
Requires-Dist: black>=23.0.0; extra == "dev"
Requires-Dist: mypy>=1.0.0; extra == "dev"
Requires-Dist: ruff>=0.1.0; extra == "dev"
Dynamic: license-file
